VSColab/__init__.py
VSColab/code.py
VSColab-0.1.4.dist-info/LICENSE
VSColab-0.1.4.dist-info/METADATA
VSColab-0.1.4.dist-info/WHEEL
VSColab-0.1.4.dist-info/top_level.txt
VSColab-0.1.4.dist-info/RECORD
