Metadata-Version: 2.1
Name: VSColab
Version: 0.1.4
Summary: SSH into Colab Notebooks and use VSCode for remote development
Home-page: https://github.com/anusikh/VSColab
Author: Anusikh Panda
Author-email: anusikh2001@gmail.com
License: MIT License
Keywords: VSColab,Colab,VS
Platform: linux
Platform: unix
Requires-Python: >3.6.0
